didak/__init__.py
didak/didak.py
didak/runner.py
didak/version.py
didak-1.0.28.dist-info/LICENSE
didak-1.0.28.dist-info/METADATA
didak-1.0.28.dist-info/WHEEL
didak-1.0.28.dist-info/top_level.txt
didak-1.0.28.dist-info/RECORD
