Metadata-Version: 2.1
Name: didak
Version: 1.0.28
Summary: Didak is a simple test case runner, that simulates input and verifies the whether the final output is correct.
Home-page: https://github.com/rmaniego/didak
Author: Rodney Maniego Jr.
Author-email: rod.maniego23@gmail.com
License: MIT
Download-URL: https://github.com/rmaniego/didak/archive/v1.0.tar.gz
Keywords: Python,test,testcase,automation
Platform: UNKNOWN
Classifier: Development Status :: 5 - Production/Stable
Classifier: Intended Audience :: Developers
Classifier: Topic :: Software Development :: Build Tools
Classifier: License :: OSI Approved :: MIT License
Classifier: Programming Language :: Python :: 3
Requires-Python: >=3.6
License-File: LICENSE
Requires-Dist: arkivist
Requires-Dist: maguro
Requires-Dist: autopep8
